hydra_plugins/hydra_slurm_rich_launcher/__init__.py
hydra_plugins/hydra_slurm_rich_launcher/_progress_handler.py
hydra_plugins/hydra_slurm_rich_launcher/_slurm_watcher.py
hydra_plugins/hydra_slurm_rich_launcher/config.py
hydra_plugins/hydra_slurm_rich_launcher/slurm_rich_launcher.py
hydra_plugins/hydra_slurm_rich_launcher/utils.py
hydra_slurm_rich_launcher-1.1.2.dist-info/METADATA
hydra_slurm_rich_launcher-1.1.2.dist-info/WHEEL
hydra_slurm_rich_launcher-1.1.2.dist-info/licenses/LICENSE
hydra_slurm_rich_launcher-1.1.2.dist-info/RECORD
