Metadata-Version: 2.4
Name: hydra-slurm-rich-launcher
Version: 1.1.2
Summary: A rich, visual interface for easily starting and monitoring your Hydra applications on SLURM clusters
License: MIT
License-File: LICENSE
Keywords: hydra,slurm,rich,launcher,command-line,cli,scheduler,monitoring,visualization
Author: Christoph Reinders
Author-email: reinders@tnt.uni-hannover.de
Requires-Python: >=3.9,<4.0
Classifier: License :: OSI Approved :: MIT License
Classifier: Programming Language :: Python :: 3
Classifier: Programming Language :: Python :: 3.9
Classifier: Programming Language :: Python :: 3.10
Classifier: Programming Language :: Python :: 3.11
Classifier: Programming Language :: Python :: 3.12
Classifier: Programming Language :: Python :: 3.13
Classifier: Programming Language :: Python :: 3.14
Requires-Dist: hydra-core (>=1.1.0)
Requires-Dist: rich (>=11.0.0)
Requires-Dist: submitit (>=1.3.3,<2.0.0)
Project-URL: Homepage, https://github.com/creinders/hydra-slurm-rich-launcher
